jupyterlab_kernelspy/__init__.py
jupyterlab_kernelspy/_version.py
jupyterlab_kernelspy-4.0.0.data/data/share/jupyter/labextensions/jupyterlab-kernelspy/package.json
jupyterlab_kernelspy-4.0.0.data/data/share/jupyter/labextensions/jupyterlab-kernelspy/static/255.9946fcf68145195b2f3e.js
jupyterlab_kernelspy-4.0.0.data/data/share/jupyter/labextensions/jupyterlab-kernelspy/static/598.1b1fd77f255e244435d4.js
jupyterlab_kernelspy-4.0.0.data/data/share/jupyter/labextensions/jupyterlab-kernelspy/static/747.fe81faa203ef14c6dc69.js
jupyterlab_kernelspy-4.0.0.data/data/share/jupyter/labextensions/jupyterlab-kernelspy/static/remoteEntry.35427e78d5ec24a32599.js
jupyterlab_kernelspy-4.0.0.data/data/share/jupyter/labextensions/jupyterlab-kernelspy/static/style.js
jupyterlab_kernelspy-4.0.0.data/data/share/jupyter/labextensions/jupyterlab-kernelspy/static/third-party-licenses.json
jupyterlab_kernelspy-4.0.0.data/data/share/jupyter/labextensions/jupyterlab-kernelspy/install.json
jupyterlab_kernelspy-4.0.0.dist-info/METADATA
jupyterlab_kernelspy-4.0.0.dist-info/WHEEL
jupyterlab_kernelspy-4.0.0.dist-info/licenses/LICENSE
jupyterlab_kernelspy-4.0.0.dist-info/RECORD
