Metadata-Version: 2.1
Name: jupyterlab_kernelspy
Version: 4.0.0
Summary: A Jupyter Lab extension for inspecting messages to/from a kernel
Project-URL: Homepage, https://github.com/jupyterlab-contrib/jupyterlab-kernelspy
Project-URL: Bug Tracker, https://github.com/jupyterlab-contrib/jupyterlab-kernelspy/issues
Project-URL: Repository, https://github.com/jupyterlab-contrib/jupyterlab-kernelspy.git
Author: Vidar Tonaas Fauske
License: # Licensing terms
License-File: LICENSE
Classifier: Framework :: Jupyter
Classifier: Framework :: Jupyter :: JupyterLab
Classifier: Framework :: Jupyter :: JupyterLab :: 4
Classifier: Framework :: Jupyter :: JupyterLab :: Extensions
Classifier: Framework :: Jupyter :: JupyterLab :: Extensions :: Prebuilt
Classifier: License :: OSI Approved :: BSD License
Classifier: Programming Language :: Python
Classifier: Programming Language :: Python :: 3
Classifier: Programming Language :: Python :: 3.8
Classifier: Programming Language :: Python :: 3.9
Classifier: Programming Language :: Python :: 3.10
Classifier: Programming Language :: Python :: 3.11
Requires-Python: >=3.8
